cep/__init__.py
cep/client.py
cep/cuenta.py
cep/exc.py
cep/py.typed
cep/transferencia.py
cep/version.py
tests/__init__.py
tests/conftest.py
tests/test_client.py
tests/test_transferencia.py
cepmex-1.0.0.dist-info/LICENSE
cepmex-1.0.0.dist-info/METADATA
cepmex-1.0.0.dist-info/WHEEL
cepmex-1.0.0.dist-info/top_level.txt
cepmex-1.0.0.dist-info/RECORD
